subtotals.py
subtotals-0.1.2.dist-info/LICENSE
subtotals-0.1.2.dist-info/WHEEL
subtotals-0.1.2.dist-info/METADATA
subtotals-0.1.2.dist-info/RECORD
